snake_gym/__init__.py
snake_gym-1.8.dist-info/LICENSE.md
snake_gym-1.8.dist-info/METADATA
snake_gym-1.8.dist-info/WHEEL
snake_gym-1.8.dist-info/top_level.txt
snake_gym-1.8.dist-info/RECORD
