Metadata-Version: 2.1
Name: snake-gym
Version: 1.8
Summary: Gym environment for Snake
Home-page: https://github.com/vivek3141/snake-gym
Author: Vivek Verma
Author-email: vivnps.verma@gmail.com
License: MIT
Platform: UNKNOWN
Classifier: Programming Language :: Python :: 3
Classifier: License :: OSI Approved :: MIT License
Classifier: Operating System :: OS Independent
